{
  "recentFiles": [
    {
      "basename": "Ruido impulsivo",
      "path": "Ruido impulsivo.md"
    },
    {
      "basename": "Ruido",
      "path": "Ruido.md"
    },
    {
      "basename": "Ruido térmico",
      "path": "Ruido térmico.md"
    },
    {
      "basename": "Diafonía",
      "path": "Diafonía.md"
    },
    {
      "basename": "Ruido de intermodulación",
      "path": "Ruido de intermodulación.md"
    },
    {
      "basename": "Constante de Boltzmann",
      "path": "Constante de Boltzmann.md"
    },
    {
      "basename": "Distorsión de retardo",
      "path": "Comunicación de Datos/Distorsión de retardo.md"
    },
    {
      "basename": "Atenuación",
      "path": "Comunicación de Datos/Atenuación.md"
    },
    {
      "basename": "Ecualización",
      "path": "Comunicación de Datos/Ecualización.md"
    },
    {
      "basename": "Transmisión digital",
      "path": "Comunicación de Datos/Transmisión digital.md"
    },
    {
      "basename": "Repetidor",
      "path": "Comunicación de Datos/Repetidor.md"
    },
    {
      "basename": "Amplificador",
      "path": "Comunicación de Datos/Amplificador.md"
    },
    {
      "basename": "Transmisión analógica",
      "path": "Comunicación de Datos/Transmisión analógica.md"
    },
    {
      "basename": "Señal analógica",
      "path": "Comunicación de Datos/Señal analógica.md"
    },
    {
      "basename": "Codec",
      "path": "Comunicación de Datos/Codec.md"
    },
    {
      "basename": "Señal digital",
      "path": "Comunicación de Datos/Señal digital.md"
    },
    {
      "basename": "Módem",
      "path": "Comunicación de Datos/Módem.md"
    },
    {
      "basename": "Dato analógico",
      "path": "Comunicación de Datos/Dato analógico.md"
    },
    {
      "basename": "Dato digital",
      "path": "Comunicación de Datos/Dato digital.md"
    },
    {
      "basename": "Señal",
      "path": "Comunicación de Datos/Señal.md"
    },
    {
      "basename": "Espectro",
      "path": "Comunicación de Datos/Espectro.md"
    },
    {
      "basename": "Ancho de banda absoluto",
      "path": "Comunicación de Datos/Ancho de banda absoluto.md"
    },
    {
      "basename": "Ancho de banda",
      "path": "Comunicación de Datos/Ancho de banda.md"
    },
    {
      "basename": "Componente continua",
      "path": "Comunicación de Datos/Componente continua.md"
    },
    {
      "basename": "Frecuencia",
      "path": "Comunicación de Datos/Frecuencia.md"
    },
    {
      "basename": "Frecuencia fundamental",
      "path": "Comunicación de Datos/Frecuencia fundamental.md"
    },
    {
      "basename": "Periodo",
      "path": "Comunicación de Datos/Periodo.md"
    },
    {
      "basename": "Frecuencia central",
      "path": "Comunicación de Datos/Frecuencia central.md"
    },
    {
      "basename": "Señalización",
      "path": "Comunicación de Datos/Señalización.md"
    },
    {
      "basename": "Presión",
      "path": "Física I/Presión.md"
    },
    {
      "basename": "Señal periódica",
      "path": "Comunicación de Datos/Señal periódica.md"
    },
    {
      "basename": "Amplitud",
      "path": "Comunicación de Datos/Amplitud.md"
    },
    {
      "basename": "Fase",
      "path": "Comunicación de Datos/Fase.md"
    },
    {
      "basename": "Longitud de onda",
      "path": "Comunicación de Datos/Longitud de onda.md"
    },
    {
      "basename": "Variaciones",
      "path": "Probabilidades y Estadísticas/Variaciones.md"
    },
    {
      "basename": "Anagramas",
      "path": "Probabilidades y Estadísticas/Anagramas.md"
    },
    {
      "basename": "Probabilidad condicional",
      "path": "Probabilidades y Estadísticas/Probabilidad condicional.md"
    },
    {
      "basename": "Combinaciones",
      "path": "Probabilidades y Estadísticas/Combinaciones.md"
    },
    {
      "basename": "Permutaciones con repetición",
      "path": "Probabilidades y Estadísticas/Permutaciones con repetición.md"
    },
    {
      "basename": "Permutaciones",
      "path": "Probabilidades y Estadísticas/Permutaciones.md"
    },
    {
      "basename": "Probabilidad",
      "path": "Probabilidades y Estadísticas/Probabilidad.md"
    },
    {
      "basename": "Probabilidades y Estadísticas",
      "path": "Probabilidades y Estadísticas/Probabilidades y Estadísticas.md"
    },
    {
      "basename": "Laplace",
      "path": "Probabilidades y Estadísticas/Laplace.md"
    },
    {
      "basename": "Evento",
      "path": "Probabilidades y Estadísticas/Evento.md"
    },
    {
      "basename": "Experimento",
      "path": "Probabilidades y Estadísticas/Experimento.md"
    },
    {
      "basename": "Límite simultáneo",
      "path": "Análisis Matemático II/Límite simultáneo.md"
    },
    {
      "basename": "Onda sinusoidal",
      "path": "Comunicación de Datos/Onda sinusoidal.md"
    },
    {
      "basename": "Full-duplex",
      "path": "Comunicación de Datos/Full-duplex.md"
    },
    {
      "basename": "Half-duplex",
      "path": "Comunicación de Datos/Half-duplex.md"
    },
    {
      "basename": "Simplex",
      "path": "Comunicación de Datos/Simplex.md"
    }
  ],
  "omittedPaths": [],
  "omittedTags": [],
  "updateOn": "file-open",
  "omitBookmarks": false,
  "maxLength": null,
  "openType": "tab"
}